LICENSE
README.md
setup.py
databricks_tooling/__init__.py
databricks_tooling/artifact_store.py
databricks_tooling/orchestrator.py
databricks_tooling/tooling.py
databricks_tooling.egg-info/PKG-INFO
databricks_tooling.egg-info/SOURCES.txt
databricks_tooling.egg-info/dependency_links.txt
databricks_tooling.egg-info/requires.txt
databricks_tooling.egg-info/top_level.txt
scripts/orchestrator_cli