Metadata-Version: 2.1
Name: databricks-tooling
Version: 0.3
Summary: A library for databricks jobs api
Home-page: UNKNOWN
Author: Eric Schles
Author-email: eschles3@jh.edu
License: MIT
Platform: UNKNOWN
Classifier: Programming Language :: Python :: 3.8
